OPCunix/__init__.py
OPCunix/command_handler.py
OPCunix/serial_manager.py
OPCunix/ucass_subprocess.py
UH_OPCunix_JGirdwood-0.1.2.dist-info/LICENSE
UH_OPCunix_JGirdwood-0.1.2.dist-info/METADATA
UH_OPCunix_JGirdwood-0.1.2.dist-info/WHEEL
UH_OPCunix_JGirdwood-0.1.2.dist-info/top_level.txt
UH_OPCunix_JGirdwood-0.1.2.dist-info/RECORD
