Metadata-Version: 2.1
Name: UH-OPCunix-JGirdwood
Version: 0.1.2
Summary: A package to interface a UCASS with a linux computer via USB-ISS
Home-page: https://github.com/JGirdwood/OPCunix
Author: Joseph Girdwood
Author-email: j.girdwood@herts.ac.uk
License: UNKNOWN
Platform: UNKNOWN
Classifier: Programming Language :: Python :: 2.7
Classifier: License :: OSI Approved :: MIT License
Classifier: Operating System :: Unix
Requires-Dist: pyserial
Requires-Dist: pyusbiss
